{"nodes": [{"id": "backend_routers_analytics_py", "label": "analytics.py", "file_type": "code", "source_file": "backend/routers/analytics.py", "source_location": "L1"}, {"id": "analytics_analyticseventpayload", "label": "AnalyticsEventPayload", "file_type": "code", "source_file": "backend/routers/analytics.py", "source_location": "L26"}, {"id": "basemodel", "label": "BaseModel", "file_type": "code", "source_file": "", "source_location": ""}, {"id": "analytics_attribute_user", "label": "_attribute_user()", "file_type": "code", "source_file": "backend/routers/analytics.py", "source_location": "L32"}, {"id": "analytics_record_event", "label": "record_event()", "file_type": "code", "source_file": "backend/routers/analytics.py", "source_location": "L46"}, {"id": "analytics_rationale_1", "label": "routers/analytics.py \u2014 Analytics event ingestion  Decoupled from content APIs so", "file_type": "rationale", "source_file": "backend/routers/analytics.py", "source_location": "L1"}, {"id": "analytics_rationale_33", "label": "Sprint 17.4 \u2014 best-effort user attribution for foot-traffic. Returns the     use", "file_type": "rationale", "source_file": "backend/routers/analytics.py", "source_location": "L33"}, {"id": "analytics_rationale_50", "label": "Record a named analytics event. Returns {ok: true} regardless of DB outcome.", "file_type": "rationale", "source_file": "backend/routers/analytics.py", "source_location": "L50"}], "edges": [{"source": "backend_routers_analytics_py", "target": "logging", "relation": "imports", "confidence": "EXTRACTED", "source_file": "backend/routers/analytics.py", "source_location": "L11", "weight": 1.0}, {"source": "backend_routers_analytics_py", "target": "uuid", "relation": "imports", "confidence": "EXTRACTED", "source_file": "backend/routers/analytics.py", "source_location": "L12", "weight": 1.0}, {"source": "backend_routers_analytics_py", "target": "datetime", "relation": "imports_from", "confidence": "EXTRACTED", "source_file": "backend/routers/analytics.py", "source_location": "L13", "weight": 1.0}, {"source": "backend_routers_analytics_py", "target": "fastapi", "relation": "imports_from", "confidence": "EXTRACTED", "source_file": "backend/routers/analytics.py", "source_location": "L15", "weight": 1.0}, {"source": "backend_routers_analytics_py", "target": "pydantic", "relation": "imports_from", "confidence": "EXTRACTED", "source_file": "backend/routers/analytics.py", "source_location": "L16", "weight": 1.0}, {"source": "backend_routers_analytics_py", "target": "database", "relation": "imports_from", "confidence": "EXTRACTED", "source_file": "backend/routers/analytics.py", "source_location": "L18", "weight": 1.0}, {"source": "backend_routers_analytics_py", "target": "routers_auth", "relation": "imports_from", "confidence": "EXTRACTED", "source_file": "backend/routers/analytics.py", "source_location": "L19", "weight": 1.0}, {"source": "backend_routers_analytics_py", "target": "analytics_analyticseventpayload", "relation": "contains", "confidence": "EXTRACTED", "source_file": "backend/routers/analytics.py", "source_location": "L26", "weight": 1.0}, {"source": "analytics_analyticseventpayload", "target": "basemodel", "relation": "inherits", "confidence": "EXTRACTED", "source_file": "backend/routers/analytics.py", "source_location": "L26", "weight": 1.0}, {"source": "backend_routers_analytics_py", "target": "analytics_attribute_user", "relation": "contains", "confidence": "EXTRACTED", "source_file": "backend/routers/analytics.py", "source_location": "L32", "weight": 1.0}, {"source": "backend_routers_analytics_py", "target": "analytics_record_event", "relation": "contains", "confidence": "EXTRACTED", "source_file": "backend/routers/analytics.py", "source_location": "L46", "weight": 1.0}, {"source": "analytics_record_event", "target": "analytics_attribute_user", "relation": "calls", "confidence": "EXTRACTED", "source_file": "backend/routers/analytics.py", "source_location": "L53", "weight": 1.0}, {"source": "analytics_rationale_1", "target": "backend_routers_analytics_py", "relation": "rationale_for", "confidence": "EXTRACTED", "source_file": "backend/routers/analytics.py", "source_location": "L1", "weight": 1.0}, {"source": "analytics_rationale_33", "target": "analytics_attribute_user", "relation": "rationale_for", "confidence": "EXTRACTED", "source_file": "backend/routers/analytics.py", "source_location": "L33", "weight": 1.0}, {"source": "analytics_rationale_50", "target": "analytics_record_event", "relation": "rationale_for", "confidence": "EXTRACTED", "source_file": "backend/routers/analytics.py", "source_location": "L50", "weight": 1.0}]}