{"nodes": [{"id": "frontend_js_reading_skill_js", "label": "reading-skill.js", "file_type": "code", "source_file": "frontend/js/reading-skill.js", "source_location": "L1"}, {"id": "reading_skill", "label": "$()", "file_type": "code", "source_file": "frontend/js/reading-skill.js", "source_location": "L19"}, {"id": "reading_skill_showstate", "label": "showState()", "file_type": "code", "source_file": "frontend/js/reading-skill.js", "source_location": "L30"}, {"id": "reading_skill_showerror", "label": "showError()", "file_type": "code", "source_file": "frontend/js/reading-skill.js", "source_location": "L36"}, {"id": "reading_skill_escapehtml", "label": "escapeHtml()", "file_type": "code", "source_file": "frontend/js/reading-skill.js", "source_location": "L38"}, {"id": "reading_skill_load", "label": "load()", "file_type": "code", "source_file": "frontend/js/reading-skill.js", "source_location": "L55"}, {"id": "reading_skill_render", "label": "render()", "file_type": "code", "source_file": "frontend/js/reading-skill.js", "source_location": "L75"}], "edges": [{"source": "frontend_js_reading_skill_js", "target": "reading_skill", "relation": "contains", "confidence": "EXTRACTED", "source_file": "frontend/js/reading-skill.js", "source_location": "L19", "weight": 1.0}, {"source": "frontend_js_reading_skill_js", "target": "reading_skill_showstate", "relation": "contains", "confidence": "EXTRACTED", "source_file": "frontend/js/reading-skill.js", "source_location": "L30", "weight": 1.0}, {"source": "frontend_js_reading_skill_js", "target": "reading_skill_showerror", "relation": "contains", "confidence": "EXTRACTED", "source_file": "frontend/js/reading-skill.js", "source_location": "L36", "weight": 1.0}, {"source": "frontend_js_reading_skill_js", "target": "reading_skill_escapehtml", "relation": "contains", "confidence": "EXTRACTED", "source_file": "frontend/js/reading-skill.js", "source_location": "L38", "weight": 1.0}, {"source": "frontend_js_reading_skill_js", "target": "reading_skill_load", "relation": "contains", "confidence": "EXTRACTED", "source_file": "frontend/js/reading-skill.js", "source_location": "L55", "weight": 1.0}, {"source": "frontend_js_reading_skill_js", "target": "reading_skill_render", "relation": "contains", "confidence": "EXTRACTED", "source_file": "frontend/js/reading-skill.js", "source_location": "L75", "weight": 1.0}, {"source": "reading_skill_showerror", "target": "reading_skill_showstate", "relation": "calls", "confidence": "EXTRACTED", "source_file": "frontend/js/reading-skill.js", "source_location": "L36", "weight": 1.0}, {"source": "reading_skill_load", "target": "reading_skill_showstate", "relation": "calls", "confidence": "EXTRACTED", "source_file": "frontend/js/reading-skill.js", "source_location": "L56", "weight": 1.0}, {"source": "reading_skill_load", "target": "reading_skill", "relation": "calls", "confidence": "EXTRACTED", "source_file": "frontend/js/reading-skill.js", "source_location": "L57", "weight": 1.0}, {"source": "reading_skill_load", "target": "reading_skill_render", "relation": "calls", "confidence": "EXTRACTED", "source_file": "frontend/js/reading-skill.js", "source_location": "L68", "weight": 1.0}, {"source": "reading_skill_load", "target": "reading_skill_showerror", "relation": "calls", "confidence": "EXTRACTED", "source_file": "frontend/js/reading-skill.js", "source_location": "L71", "weight": 1.0}]}