{"nodes": [{"id": "backend_tests_test_pg_search_py", "label": "test_pg_search.py", "file_type": "code", "source_file": "backend/tests/test_pg_search.py", "source_location": "L1"}, {"id": "test_pg_search_test_normal_term_builds_quoted_or_filter", "label": "test_normal_term_builds_quoted_or_filter()", "file_type": "code", "source_file": "backend/tests/test_pg_search.py", "source_location": "L13"}, {"id": "test_pg_search_test_comma_and_parens_are_inside_the_quotes_not_breaking_predicates", "label": "test_comma_and_parens_are_inside_the_quotes_not_breaking_predicates()", "file_type": "code", "source_file": "backend/tests/test_pg_search.py", "source_location": "L18"}, {"id": "test_pg_search_test_like_wildcards_are_escaped_to_match_literally", "label": "test_like_wildcards_are_escaped_to_match_literally()", "file_type": "code", "source_file": "backend/tests/test_pg_search.py", "source_location": "L27"}, {"id": "test_pg_search_test_double_quote_in_term_is_escaped_for_the_quoted_context", "label": "test_double_quote_in_term_is_escaped_for_the_quoted_context()", "file_type": "code", "source_file": "backend/tests/test_pg_search.py", "source_location": "L34"}, {"id": "test_pg_search_test_multiple_columns", "label": "test_multiple_columns()", "file_type": "code", "source_file": "backend/tests/test_pg_search.py", "source_location": "L39"}, {"id": "test_pg_search_rationale_1", "label": "F2 \u2014 PostgREST or_() search-filter hardening (services/pg_search.py).  Reserved", "file_type": "rationale", "source_file": "backend/tests/test_pg_search.py", "source_location": "L1"}], "edges": [{"source": "backend_tests_test_pg_search_py", "target": "services_pg_search", "relation": "imports_from", "confidence": "EXTRACTED", "source_file": "backend/tests/test_pg_search.py", "source_location": "L10", "weight": 1.0}, {"source": "backend_tests_test_pg_search_py", "target": "test_pg_search_test_normal_term_builds_quoted_or_filter", "relation": "contains", "confidence": "EXTRACTED", "source_file": "backend/tests/test_pg_search.py", "source_location": "L13", "weight": 1.0}, {"source": "backend_tests_test_pg_search_py", "target": "test_pg_search_test_comma_and_parens_are_inside_the_quotes_not_breaking_predicates", "relation": "contains", "confidence": "EXTRACTED", "source_file": "backend/tests/test_pg_search.py", "source_location": "L18", "weight": 1.0}, {"source": "backend_tests_test_pg_search_py", "target": "test_pg_search_test_like_wildcards_are_escaped_to_match_literally", "relation": "contains", "confidence": "EXTRACTED", "source_file": "backend/tests/test_pg_search.py", "source_location": "L27", "weight": 1.0}, {"source": "backend_tests_test_pg_search_py", "target": "test_pg_search_test_double_quote_in_term_is_escaped_for_the_quoted_context", "relation": "contains", "confidence": "EXTRACTED", "source_file": "backend/tests/test_pg_search.py", "source_location": "L34", "weight": 1.0}, {"source": "backend_tests_test_pg_search_py", "target": "test_pg_search_test_multiple_columns", "relation": "contains", "confidence": "EXTRACTED", "source_file": "backend/tests/test_pg_search.py", "source_location": "L39", "weight": 1.0}, {"source": "test_pg_search_rationale_1", "target": "backend_tests_test_pg_search_py", "relation": "rationale_for", "confidence": "EXTRACTED", "source_file": "backend/tests/test_pg_search.py", "source_location": "L1", "weight": 1.0}]}